{"chunk":6,"numChunks":9,"fileHash":"2QR/w/gks8Jat9bgKNiN/n9OIIEsanSxKcErf8kcNsc=","filePath":"web/static/css/styles.css","content":"/* General Styling */\n.auth-form input:focus {\n    outline: none;\n    border-color: #008CBA;\n    box-shadow: 0 0 5px rgba(0, 140, 186, 0.3);\n}\n.auth-form button {\n    width: 100%;\n    padding: 12px;\n    background: #008CBA;\n    color: white;\n    border: none;\n    border-radius: 5px;\n    font-size: 16px;\n    cursor: pointer;\n    transition: background-color 0.3s ease;\n    margin-bottom: 20px;\n}\n.auth-form button:hover {\n    background: #005f7f;\n}\n.auth-form p {\n    text-align: center;\n    margin-top: 20px;\n    color: #666;\n}\n.auth-form p a {\n    color: #008CBA;\n    text-decoration: none;\n    font-weight: 500;\n}\n.auth-form p a:hover {\n    text-decoration: underline;\n}\n.auth-form .error {\n    background-color: #ffebee;\n    color: #dc3545;\n    padding: 12px;\n    border-radius: 5px;\n    margin-bottom: 20px;\n    text-align: center;\n}\n/* Error Container */\n.error-container {\n    text-align: center;\n    padding: 40px;\n}\n.error-container h1 {\n    color: #dc3545;\n    margin-bottom: 20px;\n}\n.error-container p {\n    color: #666;\n    margin-bottom: 30px;\n    font-size: 18px;\n}\n/* Category Button Container */\n.category-button {\n    margin: 20px 0;\n    text-align: center;\n}\n/* Back to Home Button */"}