{"chunk":0,"numChunks":1,"fileHash":"InqXFOCuQlGG8l05xqJzOZu9A2C5n9JLzDlFEMndLeg=","filePath":"web/templates/login2.html","content":"<!DOCTYPE html>\n<html>\n<head>\n    <title>Login - Åland Forum</title>\n    <link rel=\"stylesheet\" href=\"/static/css/styles.css\">\n</head>\n<body>\n    <header>\n        <h1>Åland Forum</h1>\n    </header>\n    <div class=\"main-container\">\n        <div class=\"posts-feed\">\n            <div class=\"auth-form\">\n                <h1>Login</h1>\n                {{if .ErrorMessage}}\n                    <div class=\"error\">\n                        {{.ErrorMessage}}\n                    </div>\n                {{end}}\n                <form action=\"/login\" method=\"POST\">\n                    <label for=\"email\">Email:</label>\n                    <input type=\"email\" id=\"email\" name=\"email\" required>\n                    \n                    <label for=\"password\">Password:</label>\n                    <input type=\"password\" id=\"password\" name=\"password\" required>\n                    \n                    <button type=\"submit\">Login</button>\n                </form>\n                <p>Don't have an account? <a href=\"/register\">Register here</a></p>\n                <div class=\"category-button\">\n                    <a href=\"/\" class=\"back-to-home\">Back to Home</a>\n                </div>\n            </div>\n        </div>\n    </div>\n</body>\n</html>"}